etl/__init__.py
etl/utils.py
etl/api/__init__.py
etl/api/run.py
etl/api/utils.py
etl/api/api/__init__.py
etl/api/api/api.py
etl/api/api/database.py
etl/api/api/recommender.py
etl/data_preperation/__init__.py
etl/data_preperation/data_generator.py
etl/data_preperation/schema.py
etl/data_preperation/sql_interactions.py
etl/logger/__init__.py
etl/logger/logger.py
etl/movie_recommender/__init__.py
etl/movie_recommender/check.py
etl/movie_recommender/database.py
etl/movie_recommender/kki.py
etl/movie_recommender/recommender.py
etl/movie_recommender/setup.py
etl/movie_recommender/temp.db
movie_recommend-0.0.9.dist-info/METADATA
movie_recommend-0.0.9.dist-info/WHEEL
movie_recommend-0.0.9.dist-info/top_level.txt
movie_recommend-0.0.9.dist-info/RECORD
