Metadata-Version: 2.1
Name: movie-recommend
Version: 0.0.9
Summary: Movie recommendation
Home-page: UNKNOWN
Author: Group_7
License: UNKNOWN
Platform: UNKNOWN
Requires-Dist: annotated-types ==0.6.0
Requires-Dist: anyio ==3.7.1
Requires-Dist: click ==8.1.7
Requires-Dist: exceptiongroup ==1.1.3
Requires-Dist: Faker ==20.0.3
Requires-Dist: fastapi ==0.104.0
Requires-Dist: h11 ==0.14.0
Requires-Dist: httptools ==0.6.1
Requires-Dist: idna ==3.4
Requires-Dist: joblib ==1.3.2
Requires-Dist: numpy ==1.26.1
Requires-Dist: pandas ==2.1.2
Requires-Dist: pydantic ==2.4.2
Requires-Dist: pydantic-core ==2.10.1
Requires-Dist: python-dateutil ==2.8.2
Requires-Dist: python-dotenv ==1.0.0
Requires-Dist: pytz ==2023.3.post1
Requires-Dist: PyYAML ==6.0.1
Requires-Dist: scikit-learn ==1.3.2
Requires-Dist: scipy ==1.11.3
Requires-Dist: six ==1.16.0
Requires-Dist: sniffio ==1.3.0
Requires-Dist: starlette ==0.27.0
Requires-Dist: threadpoolctl ==3.2.0
Requires-Dist: typing-extensions ==4.8.0
Requires-Dist: tzdata ==2023.3
Requires-Dist: unicorn ==2.0.1.post1
Requires-Dist: uvicorn ==0.23.2
Requires-Dist: uvloop ==0.19.0
Requires-Dist: watchfiles ==0.21.0
Requires-Dist: websockets ==12.0
Requires-Dist: sqlalchemy
